odoo/addons/stock_account_product_run_fifo_hook/README.rst
odoo/addons/stock_account_product_run_fifo_hook/__init__.py
odoo/addons/stock_account_product_run_fifo_hook/__manifest__.py
odoo/addons/stock_account_product_run_fifo_hook/hooks.py
odoo/addons/stock_account_product_run_fifo_hook/i18n/es.po
odoo/addons/stock_account_product_run_fifo_hook/i18n/it.po
odoo/addons/stock_account_product_run_fifo_hook/i18n/pt_BR.po
odoo/addons/stock_account_product_run_fifo_hook/i18n/stock_account_product_run_fifo_hook.pot
odoo/addons/stock_account_product_run_fifo_hook/model/__init__.py
odoo/addons/stock_account_product_run_fifo_hook/model/product.py
odoo/addons/stock_account_product_run_fifo_hook/model/stock_valuation_layer.py
odoo/addons/stock_account_product_run_fifo_hook/readme/CONTRIBUTORS.md
odoo/addons/stock_account_product_run_fifo_hook/readme/DESCRIPTION.md
odoo/addons/stock_account_product_run_fifo_hook/readme/USAGE.md
odoo/addons/stock_account_product_run_fifo_hook/static/description/icon.png
odoo/addons/stock_account_product_run_fifo_hook/static/description/index.html
odoo_addon_stock_account_product_run_fifo_hook-18.0.1.0.1.5.dist-info/METADATA
odoo_addon_stock_account_product_run_fifo_hook-18.0.1.0.1.5.dist-info/WHEEL
odoo_addon_stock_account_product_run_fifo_hook-18.0.1.0.1.5.dist-info/top_level.txt
odoo_addon_stock_account_product_run_fifo_hook-18.0.1.0.1.5.dist-info/RECORD
