Metadata-Version: 2.1
Name: odoo-addon-stock_account_product_run_fifo_hook
Version: 18.0.1.0.1.5
Requires-Python: >=3.10
Requires-Dist: odoo==18.0.*
Summary: Add more flexibility in the run fifo method.
Home-page: https://github.com/OCA/stock-logistics-workflow
License: LGPL-3
Author: ForgeFlow, Odoo Community Association (OCA)
Author-email: support@odoo-community.org
Classifier: Programming Language :: Python
Classifier: Framework :: Odoo
Classifier: Framework :: Odoo :: 18.0
Classifier: License :: OSI Approved :: GNU Lesser General Public License v3 (LGPLv3)
